<constant_variable xmlns="http://oval.mitre.org/XMLSchema/oval-definitions-5" comment="Affected IOSXE versions" datatype="string" id="oval:org.cisecurity:var:1864" version="1">
  <value>^0*16\.0*2\.0*1$</value>
  <value>^0*16\.0*2\.0*2$</value>
  <value>^0*16\.0*3\.0*1$</value>
  <value>^0*16\.0*3\.0*1\.?a$</value>
  <value>^0*16\.0*3\.0*2$</value>
  <value>^0*16\.0*3\.0*3$</value>
  <value>^0*16\.0*3\.0*4$</value>
  <value>^0*16\.0*3\.0*5$</value>
  <value>^0*16\.0*3\.0*6$</value>
  <value>^0*16\.0*3\.0*7$</value>
  <value>^0*16\.0*3\.0*8$</value>
  <value>^0*16\.0*4\.0*1$</value>
  <value>^0*16\.0*4\.0*2$</value>
  <value>^0*16\.0*4\.0*3$</value>
  <value>^0*16\.0*5\.0*1$</value>
  <value>^0*16\.0*5\.0*1\.?b$</value>
  <value>^0*16\.0*5\.0*2$</value>
  <value>^0*16\.0*5\.0*3$</value>
  <value>^0*16\.0*6\.0*1$</value>
  <value>^0*16\.0*6\.0*2$</value>
  <value>^0*16\.0*6\.0*3$</value>
  <value>^0*16\.0*6\.0*4$</value>
  <value>^0*16\.0*6\.0*4\.?s$</value>
  <value>^0*16\.0*7\.0*1$</value>
  <value>^0*16\.0*7\.0*1\.?a$</value>
  <value>^0*16\.0*7\.0*1\.?b$</value>
  <value>^0*16\.0*7\.0*2$</value>
  <value>^0*16\.0*7\.0*3$</value>
  <value>^0*16\.0*7\.0*4$</value>
  <value>^0*16\.0*8\.0*1$</value>
  <value>^0*16\.0*8\.0*1\.?a$</value>
  <value>^0*16\.0*8\.0*1\.?c$</value>
  <value>^0*16\.0*8\.0*1\.?d$</value>
  <value>^0*16\.0*8\.0*1\.?e$</value>
  <value>^0*16\.0*8\.0*1\.?s$</value>
  <value>^0*16\.0*8\.0*2$</value>
  <value>^0*16\.0*8\.0*3$</value>
  <value>^0*16\.0*9\.0*1$</value>
  <value>^0*16\.0*9\.0*1\.?a$</value>
  <value>^0*16\.0*9\.0*1\.?c$</value>
  <value>^0*16\.0*9\.0*1\.?s$</value>
  <value>^0*17\.0*2\.0*1$</value>
  <value>^0*17\.0*3\.0*1$</value>
  <value>^0*17\.0*4\.0*1$</value>
  <value>^0*17\.0*5\.0*1$</value>
  <value>^0*17\.0*6\.0*1$</value>
  <value>^0*3\.0*10\.0*0\.?S$</value>
  <value>^0*3\.0*10\.0*10\.?S$</value>
  <value>^0*3\.0*10\.0*1\.?S$</value>
  <value>^0*3\.0*10\.0*2\.?S$</value>
  <value>^0*3\.0*10\.0*2\.?a\.?S$</value>
  <value>^0*3\.0*10\.0*2\.?t\.?S$</value>
  <value>^0*3\.0*10\.0*3\.?S$</value>
  <value>^0*3\.0*10\.0*4\.?S$</value>
  <value>^0*3\.0*10\.0*5\.?S$</value>
  <value>^0*3\.0*10\.0*6\.?S$</value>
  <value>^0*3\.0*10\.0*7\.?S$</value>
  <value>^0*3\.0*10\.0*8\.?S$</value>
  <value>^0*3\.0*10\.0*8\.?a\.?S$</value>
  <value>^0*3\.0*10\.0*9\.?S$</value>
  <value>^0*3\.0*11\.0*0\.?S$</value>
  <value>^0*3\.0*11\.0*1\.?S$</value>
  <value>^0*3\.0*11\.0*2\.?S$</value>
  <value>^0*3\.0*11\.0*3\.?S$</value>
  <value>^0*3\.0*11\.0*4\.?S$</value>
  <value>^0*3\.0*12\.0*0\.?S$</value>
  <value>^0*3\.0*12\.0*0\.?a\.?S$</value>
  <value>^0*3\.0*12\.0*1\.?S$</value>
  <value>^0*3\.0*12\.0*2\.?S$</value>
  <value>^0*3\.0*12\.0*3\.?S$</value>
  <value>^0*3\.0*12\.0*4\.?S$</value>
  <value>^0*3\.0*13\.0*0\.?S$</value>
  <value>^0*3\.0*13\.0*0\.?a\.?S$</value>
  <value>^0*3\.0*13\.0*10\.?S$</value>
  <value>^0*3\.0*13\.0*1\.?S$</value>
  <value>^0*3\.0*13\.0*2\.?S$</value>
  <value>^0*3\.0*13\.0*2\.?a\.?S$</value>
  <value>^0*3\.0*13\.0*3\.?S$</value>
  <value>^0*3\.0*13\.0*4\.?S$</value>
  <value>^0*3\.0*13\.0*5\.?S$</value>
  <value>^0*3\.0*13\.0*5\.?a\.?S$</value>
  <value>^0*3\.0*13\.0*6\.?S$</value>
  <value>^0*3\.0*13\.0*6\.?a\.?S$</value>
  <value>^0*3\.0*13\.0*6\.?b\.?S$</value>
  <value>^0*3\.0*13\.0*7\.?S$</value>
  <value>^0*3\.0*13\.0*7\.?a\.?S$</value>
  <value>^0*3\.0*13\.0*8\.?S$</value>
  <value>^0*3\.0*13\.0*9\.?S$</value>
  <value>^0*3\.0*14\.0*0\.?S$</value>
  <value>^0*3\.0*14\.0*1\.?S$</value>
  <value>^0*3\.0*14\.0*2\.?S$</value>
  <value>^0*3\.0*14\.0*3\.?S$</value>
  <value>^0*3\.0*14\.0*4\.?S$</value>
  <value>^0*3\.0*15\.0*0\.?S$</value>
  <value>^0*3\.0*15\.0*1\.?S$</value>
  <value>^0*3\.0*15\.0*1\.?c\.?S$</value>
  <value>^0*3\.0*15\.0*2\.?S$</value>
  <value>^0*3\.0*15\.0*3\.?S$</value>
  <value>^0*3\.0*15\.0*4\.?S$</value>
  <value>^0*3\.0*16\.0*0\.?S$</value>
  <value>^0*3\.0*16\.0*0\.?c\.?S$</value>
  <value>^0*3\.0*16\.0*1\.?S$</value>
  <value>^0*3\.0*16\.0*1\.?a\.?S$</value>
  <value>^0*3\.0*16\.0*2\.?S$</value>
  <value>^0*3\.0*16\.0*2\.?b\.?S$</value>
  <value>^0*3\.0*16\.0*3\.?S$</value>
  <value>^0*3\.0*16\.0*4\.?a\.?S$</value>
  <value>^0*3\.0*16\.0*4\.?b\.?S$</value>
  <value>^0*3\.0*16\.0*4\.?c\.?S$</value>
  <value>^0*3\.0*16\.0*4\.?d\.?S$</value>
  <value>^0*3\.0*16\.0*4\.?e\.?S$</value>
  <value>^0*3\.0*16\.0*4\.?g\.?S$</value>
  <value>^0*3\.0*16\.0*5\.?S$</value>
  <value>^0*3\.0*16\.0*5\.?a\.?S$</value>
  <value>^0*3\.0*16\.0*5\.?b\.?S$</value>
  <value>^0*3\.0*16\.0*6\.?S$</value>
  <value>^0*3\.0*16\.0*6\.?b\.?S$</value>
  <value>^0*3\.0*16\.0*7\.?S$</value>
  <value>^0*3\.0*16\.0*7\.?a\.?S$</value>
  <value>^0*3\.0*16\.0*7\.?b\.?S$</value>
  <value>^0*3\.0*16\.0*8\.?S$</value>
  <value>^0*3\.0*16\.0*9\.?S$</value>
  <value>^0*3\.0*17\.0*0\.?S$</value>
  <value>^0*3\.0*17\.0*1\.?S$</value>
  <value>^0*3\.0*17\.0*1\.?a\.?S$</value>
  <value>^0*3\.0*17\.0*2\.?S$</value>
  <value>^0*3\.0*17\.0*3\.?S$</value>
  <value>^0*3\.0*17\.0*4\.?S$</value>
  <value>^0*3\.0*18\.0*0\.?a\.?S$</value>
  <value>^0*3\.0*18\.0*1\.?S\.?P$</value>
  <value>^0*3\.0*18\.0*1\.?a\.?S\.?P$</value>
  <value>^0*3\.0*18\.0*2\.?a\.?S\.?P$</value>
  <value>^0*3\.0*18\.0*3\.?S\.?P$</value>
  <value>^0*3\.0*18\.0*3\.?a\.?S\.?P$</value>
  <value>^0*3\.0*18\.0*3\.?b\.?S\.?P$</value>
  <value>^0*3\.0*18\.0*4\.?S\.?P$</value>
  <value>^0*3\.0*18\.0*5\.?S\.?P$</value>
  <value>^0*3\.0*18\.0*6\.?S\.?P$</value>
  <value>^0*3\.0*3\.0*0\.?X\.?O$</value>
  <value>^0*3\.0*3\.0*1\.?X\.?O$</value>
  <value>^0*3\.0*3\.0*2\.?X\.?O$</value>
  <value>^0*3\.0*6\.0*5\.?b\.?E$</value>
  <value>^0*3\.0*7\.0*0\.?S$</value>
  <value>^0*3\.0*7\.0*0\.?b\.?S$</value>
  <value>^0*3\.0*7\.0*1\.?S$</value>
  <value>^0*3\.0*7\.0*2\.?S$</value>
  <value>^0*3\.0*7\.0*2\.?t\.?S$</value>
  <value>^0*3\.0*7\.0*3\.?S$</value>
  <value>^0*3\.0*7\.0*4\.?S$</value>
  <value>^0*3\.0*7\.0*4\.?a\.?S$</value>
  <value>^0*3\.0*7\.0*5\.?S$</value>
  <value>^0*3\.0*7\.0*6\.?S$</value>
  <value>^0*3\.0*7\.0*7\.?S$</value>
  <value>^0*3\.0*7\.0*8\.?S$</value>
  <value>^0*3\.0*8\.0*0\.?S$</value>
  <value>^0*3\.0*8\.0*1\.?S$</value>
  <value>^0*3\.0*8\.0*2\.?S$</value>
  <value>^0*3\.0*9\.0*0\.?S$</value>
  <value>^0*3\.0*9\.0*0\.?a\.?S$</value>
  <value>^0*3\.0*9\.0*1\.?S$</value>
  <value>^0*3\.0*9\.0*2\.?S$</value>
</constant_variable>
