<file_object xmlns="http://oval.mitre.org/XMLSchema/oval-definitions-5#windows" xmlns:oval-def="http://oval.mitre.org/XMLSchema/oval-definitions-5" id="oval:org.cisecurity:obj:6414" version="1" comment="netapi32.dll (32-bit version) (10.x)">
  <oval-def:set>
    <oval-def:object_reference>oval:org.cisecurity:obj:6518</oval-def:object_reference>
    <oval-def:filter action="exclude">oval:org.cisecurity:ste:23658</oval-def:filter>
    <oval-def:filter action="exclude">oval:org.cisecurity:ste:23484</oval-def:filter>
  </oval-def:set>
</file_object>
