<oval-def:definition xmlns:oval-def="http://oval.mitre.org/XMLSchema/oval-definitions-5" class="patch" id="oval:com.altx-soft.nix:def:27326" version="2">
  <oval-def:metadata>
    <oval-def:title>DSA-3699-1 -- virtualbox -- end-of-life</oval-def:title>
    <oval-def:affected family="unix">
      <oval-def:platform>Debian 8</oval-def:platform>
      <oval-def:product>virtualbox</oval-def:product>
    </oval-def:affected>
    <oval-def:reference ref_id="DSA-3699-1" ref_url="https://www.debian.org/security/dsa-3699" source="VENDOR" />
    <oval-def:description>Upstream support for the 4.3 release series has ended and since no information is available which would allow backports of isolated security fixes, security support for virtualbox in jessie needed to be ended as well.</oval-def:description>
    <oval-def:oval_repository>
      <oval-def:dates>
        <oval-def:submitted date="2016-11-03T12:47:22">
          <oval-def:contributor organization="ALTX-SOFT">Maria Mikhno</oval-def:contributor>
        </oval-def:submitted>
      </oval-def:dates>
      <oval-def:status>INITIAL SUBMISSION</oval-def:status>
    </oval-def:oval_repository>
  </oval-def:metadata>
  <oval-def:criteria>
    <oval-def:extend_definition comment="Debian 8 is installed" definition_ref="oval:org.mitre.oval:def:28919" />
    <oval-def:criterion comment="virtualbox is less than or equal 0:4.3.36-dfsg-1+deb8u1" test_ref="oval:ru.altx-soft.nix:tst:67387" />
  </oval-def:criteria>
</oval-def:definition>
